{
    "persons": [
        {
            "id"            : 1,
            "name"          : "Van Impe",
            "first_name"    : "Charlien",
            "email"         : "charlienvanimpe@yahoo.com",
            "phone"         : "+32497221988",
            "address_id"    : null
        },
        {
            "id"            : 2,
            "name"          : "Doe",
            "first_name"    : "John",
            "email"         : "johndoe@gmail.com",
            "phone"         : "+32471234567",
            "address_id"    : null
        },
        {
            "id"            : 3,
            "name"          : "Smith",
            "first_name"    : "Jane",
            "email"         : "janesmith@hotmail.com",
            "phone"         : "+32475432123",
            "address_id"    : null
        },
        {
            "id"            : 4,
            "name"          : "Johnson",
            "first_name"    : "Michael",
            "email"         : "michaeljohnson@yahoo.com",
            "phone"         : "+32475678901",
            "address_id"    : null
        },
        {
            "id"            : 5,
            "name"          : "Brown",
            "first_name"    : "Emily",
            "email"         : "emilybrown@gmail.com",
            "phone"         : "+32471239876",
            "address_id"    : null
        }
    ]
}